LICENSE.txt
MANIFEST.in
README.rst
requirements.txt
setup.py
aws_hostname/__init__.py
aws_hostname.egg-info/PKG-INFO
aws_hostname.egg-info/SOURCES.txt
aws_hostname.egg-info/dependency_links.txt
aws_hostname.egg-info/requires.txt
aws_hostname.egg-info/top_level.txt
aws_hostname.egg-info/zip-safe
bin/aws-hostname