Metadata-Version: 1.1
Name: aws-hostname
Version: 0.0.4
Summary: Outputs a valid hostname for a given AWS instance
Home-page: https://github.com/josegonzalez/python-aws-hostname
Author: Jose Diaz-Gonzalez
Author-email: email@josediazgonzalez.com
License: Copyright (c) 2014 Jose Diaz-Gonzalez
